tasho/__init__.py
tasho/autogenerateid.py
tasho/chunk.py
tasho/console.py
tasho/document.py
tasho/exceptions.py
tasho/polyfill.py
tasho/query_engine.py
tasho/table.py
tasho-0.0.3.dist-info/LICENSE
tasho-0.0.3.dist-info/METADATA
tasho-0.0.3.dist-info/WHEEL
tasho-0.0.3.dist-info/top_level.txt
tasho-0.0.3.dist-info/RECORD
