Metadata-Version: 2.1
Name: tasho
Version: 0.0.3
Summary: A performant and lightweight NOSQL Database
Home-page: https://github.com/nokusukun/TashoDB
Author: Natsuko H.
Author-email: nokusukun@yahoo.co.jp
License: UNKNOWN
Platform: UNKNOWN
Classifier: Programming Language :: Python :: 3
Classifier: License :: OSI Approved :: MIT License
Classifier: Operating System :: OS Independent
